MANIFEST.in
README.md
VERSION
requirements.txt
setup.py
apsconnectcli/__init__.py
apsconnectcli/action_logger.py
apsconnectcli/apsconnect.py
apsconnectcli/config.py
apsconnectcli/hub.py
apsconnectcli/package.py
apsconnectcli.egg-info/PKG-INFO
apsconnectcli.egg-info/SOURCES.txt
apsconnectcli.egg-info/dependency_links.txt
apsconnectcli.egg-info/entry_points.txt
apsconnectcli.egg-info/requires.txt
apsconnectcli.egg-info/top_level.txt