Metadata-Version: 1.1
Name: apsconnectcli
Version: 17.1
Summary: A command line tool for APS connector installation on Odin Automation in the relaxed way.
Home-page: https://github.com/ingrammicro/apsconnect-cli
Author: Ingram Micro
Author-email: UNKNOWN
License: Apache Software License
Keywords: aps apsconnect connector automation
Platform: UNKNOWN
Classifier: Development Status :: 4 - Beta
Classifier: Intended Audience :: Developers
Classifier: Topic :: Software Development :: Libraries :: Python Modules
Classifier: License :: OSI Approved :: Apache Software License
Classifier: Programming Language :: Python
Classifier: Programming Language :: Python :: 2
Classifier: Programming Language :: Python :: 2.7
Classifier: Programming Language :: Python :: 3
Classifier: Programming Language :: Python :: 3.4
Classifier: Programming Language :: Python :: 3.5
Classifier: Programming Language :: Python :: 3.6
Classifier: Operating System :: OS Independent
Classifier: Operating System :: POSIX
Classifier: Operating System :: MacOS
Classifier: Operating System :: Unix
